{
	"Records": [
		{
			"eventID": "shardId-000000000000:49545115243490985018280067714973144582180062593244200961",
			"eventVersion": "1.0",
			"kinesis": {
				"approximateArrivalTimestamp": 1428537600,
				"partitionKey": "partitionKey-3",
				"data": "eyJmb28iOiJiYXIifQ==",
				"kinesisSchemaVersion": "1.0",
				"sequenceNumber": "49545115243490985018280067714973144582180062593244200961"
			},
			"invokeIdentityArn": "arn:aws:iam::EXAMPLE",
			"eventName": "aws:kinesis:record",
			"eventSourceARN": "arn:aws:kinesis:MyStream",
			"eventSource": "aws:kinesis",
			"awsRegion": "us-east-1"
		},
		{
			"eventID": "shardId-000000000000:49545115243490985018280067714973144582180062593244200961",
			"eventVersion": "1.0",
			"kinesis": {
				"approximateArrivalTimestamp": 1428537600,
				"partitionKey": "partitionKey-3",
				"data": "eyJ1bmljb3JuIjoicmFpbmJvdyJ9",
				"kinesisSchemaVersion": "1.0",
				"sequenceNumber": "49545115243490985018280067714973144582180062593244200961"
			},
			"invokeIdentityArn": "arn:aws:iam::EXAMPLE",
			"eventName": "aws:kinesis:record",
			"eventSourceARN": "arn:aws:kinesis:MyStream",
			"eventSource": "aws:kinesis",
			"awsRegion": "us-east-1"
		}
	]
}
